nfdi4culture/__init__.py
nfdi4culture/cto.ttl
nfdi4culture/cto1.py
nfdi4culture/helpers.py
nfdi4culture/marc.py
nfdi4culture/ontology.py
nfdi4culture/schema.ttl
nfdi4culture-0.3.dist-info/LICENSE.txt
nfdi4culture-0.3.dist-info/METADATA
nfdi4culture-0.3.dist-info/WHEEL
nfdi4culture-0.3.dist-info/RECORD
