Metadata-Version: 2.1
Name: nfdi4culture
Version: 0.3
Summary: This package provides a Python interface to the NFDI4Culture infrastructure.
Home-page: https://nfdi4culture.de/
License: MIT
Author: Etienne Posthumus
Author-email: ep@epoz.org
Requires-Python: >=3.7,<4.0
Classifier: License :: OSI Approved :: MIT License
Classifier: Programming Language :: Python :: 3
Classifier: Programming Language :: Python :: 3.7
Classifier: Programming Language :: Python :: 3.8
Classifier: Programming Language :: Python :: 3.9
Classifier: Programming Language :: Python :: 3.10
Classifier: Programming Language :: Python :: 3.11
Classifier: Programming Language :: Python :: 3.12
Requires-Dist: validators (>=0.28.1,<0.29.0)
